setup.py
src/ConfigWrapper.egg-info/PKG-INFO
src/ConfigWrapper.egg-info/SOURCES.txt
src/ConfigWrapper.egg-info/dependency_links.txt
src/ConfigWrapper.egg-info/top_level.txt
src/configwrapper/__init__.py
src/configwrapper/schema.py
src/configwrapper/section.py
src/configwrapper/options/__init__.py
src/configwrapper/options/_option.py
src/configwrapper/options/_options.py
src/configwrapper/options/collections.py
src/configwrapper/options/enums.py
src/configwrapper/options/numeric.py
src/configwrapper/options/relations.py
src/configwrapper/options/strings.py