Metadata-Version: 1.0
Name: ConfigWrapper
Version: 0.4.5
Summary: Schema support for ConfigParser
Home-page: UNKNOWN
Author: Lai Tash
Author-email: lai.tash@gmail.com
License: UNKNOWN
Platform: UNKNOWN
